reprobench/__init__.py
reprobench/console/decorators.py
reprobench/console/main.py
reprobench/console/status.py
reprobench/core/analyzer.py
reprobench/core/base.py
reprobench/core/bootstrap/__init__.py
reprobench/core/bootstrap/client.py
reprobench/core/bootstrap/server.py
reprobench/core/db.py
reprobench/core/events.py
reprobench/core/exceptions.py
reprobench/core/observers.py
reprobench/core/schema.py
reprobench/core/server.py
reprobench/core/sysinfo.py
reprobench/core/worker.py
reprobench/executors/__init__.py
reprobench/executors/base.py
reprobench/executors/db.py
reprobench/executors/events.py
reprobench/executors/psmon.py
reprobench/managers/__init__.py
reprobench/managers/base.py
reprobench/managers/local/__init__.py
reprobench/managers/local/manager.py
reprobench/managers/slurm/__init__.py
reprobench/managers/slurm/manager.py
reprobench/managers/slurm/utils.py
reprobench/statistics/plots/__init__.py
reprobench/statistics/plots/base.py
reprobench/statistics/plots/cactus/__init__.py
reprobench/statistics/plots/cactus/template.ipynb
reprobench/statistics/tables/__init__.py
reprobench/statistics/tables/base.py
reprobench/statistics/tables/run.py
reprobench/task_sources/base.py
reprobench/task_sources/doi/__init__.py
reprobench/task_sources/doi/base.py
reprobench/task_sources/doi/zenodo.py
reprobench/task_sources/file.py
reprobench/task_sources/url.py
reprobench/tools/executable.py
reprobench/utils.py
reprobench-0.11.1.dist-info/entry_points.txt
reprobench-0.11.1.dist-info/LICENSE
reprobench-0.11.1.dist-info/WHEEL
reprobench-0.11.1.dist-info/METADATA
reprobench-0.11.1.dist-info/RECORD
