Metadata-Version: 2.1
Name: reprobench
Version: 0.11.1
Summary: Reproducible Benchmark for Everyone
Home-page: UNKNOWN
License: MIT
Author: Rakha Kanz Kautsar
Author-email: rkkautsar@gmail.com
Requires-Python: >=3.6
Classifier: License :: OSI Approved :: MIT License
Classifier: Programming Language :: Python :: 3
Classifier: Programming Language :: Python :: 3.6
Classifier: Programming Language :: Python :: 3.7
Provides-Extra: all
Provides-Extra: analytics
Provides-Extra: client
Provides-Extra: pcs
Provides-Extra: psmon
Provides-Extra: server
Provides-Extra: sysinfo
Requires-Dist: apsw (>=3.9,<4.0); extra == "server" or extra == "analytics" or extra == "all"
Requires-Dist: click (>=7.0,<8.0)
Requires-Dist: configspace (>=0.4.10,<0.5.0); extra == "pcs" or extra == "all"
Requires-Dist: gevent (>=1.4,<2.0); extra == "server" or extra == "all"
Requires-Dist: loguru (>=0.2.5,<0.3.0)
Requires-Dist: msgpack-python (>=0.5.6,<0.6.0); extra == "server" or extra == "client" or extra == "all"
Requires-Dist: numpy (>=1.16,<2.0)
Requires-Dist: pandas (>=0.24.2,<0.25.0); extra == "analytics" or extra == "all"
Requires-Dist: papermill (>=0.19.1,<1.1.0); extra == "analytics" or extra == "all"
Requires-Dist: pathspec (>=0.5.9,<0.6.0)
Requires-Dist: peewee (>=3.9,<4.0); extra == "server" or extra == "analytics" or extra == "all"
Requires-Dist: psmon (>=1.1.0,<2.0.0); extra == "psmon" or extra == "all"
Requires-Dist: psutil (>=5.6,<6.0); extra == "sysinfo" or extra == "all"
Requires-Dist: py-cpuinfo (>=4,<6); extra == "sysinfo" or extra == "all"
Requires-Dist: pyzmq (>=18.0,<19.0); extra == "server" or extra == "client" or extra == "all"
Requires-Dist: requests (>=2.21,<3.0)
Requires-Dist: retrying (>=1.3,<2.0)
Requires-Dist: sshtunnel (>=0.1.5,<0.2.0)
Requires-Dist: strictyaml (>=1.0,<2.0)
Requires-Dist: tqdm (>=4.31,<5.0)
